odoo/addons/stock_lot_create_set_reference/README.rst
odoo/addons/stock_lot_create_set_reference/__init__.py
odoo/addons/stock_lot_create_set_reference/__manifest__.py
odoo/addons/stock_lot_create_set_reference/i18n/es.po
odoo/addons/stock_lot_create_set_reference/models/__init__.py
odoo/addons/stock_lot_create_set_reference/models/stock_lot.py
odoo/addons/stock_lot_create_set_reference/models/stock_move_line.py
odoo/addons/stock_lot_create_set_reference/models/stock_picking_type.py
odoo/addons/stock_lot_create_set_reference/readme/CONFIGURE.md
odoo/addons/stock_lot_create_set_reference/readme/CONTRIBUTORS.md
odoo/addons/stock_lot_create_set_reference/readme/DESCRIPTION.md
odoo/addons/stock_lot_create_set_reference/readme/USAGE.md
odoo/addons/stock_lot_create_set_reference/static/description/icon.png
odoo/addons/stock_lot_create_set_reference/static/description/index.html
odoo/addons/stock_lot_create_set_reference/tests/__init__.py
odoo/addons/stock_lot_create_set_reference/tests/test_stock_lot_create_set_reference.py
odoo/addons/stock_lot_create_set_reference/views/stock_picking_type_views.xml
odoo_addon_stock_lot_create_set_reference-17.0.1.0.0.1.dist-info/METADATA
odoo_addon_stock_lot_create_set_reference-17.0.1.0.0.1.dist-info/WHEEL
odoo_addon_stock_lot_create_set_reference-17.0.1.0.0.1.dist-info/top_level.txt
odoo_addon_stock_lot_create_set_reference-17.0.1.0.0.1.dist-info/RECORD
