Metadata-Version: 2.1
Name: odoo-addon-stock_lot_create_set_reference
Version: 17.0.1.0.0.1
Requires-Python: >=3.10
Requires-Dist: odoo-addon-stock_picking_auto_create_lot_sequence>=17.0dev,<17.1dev
Requires-Dist: odoo>=17.0a,<17.1dev
Summary: Set the name of the lot as the reference
Home-page: https://github.com/sygel-technology/sy-stock-logistics-workflow
License: AGPL-3
Author: Sygel, Odoo Community Association (OCA)
Author-email: support@odoo-community.org
Classifier: Programming Language :: Python
Classifier: Framework :: Odoo
Classifier: Framework :: Odoo :: 17.0
Classifier: License :: OSI Approved :: GNU Affero General Public License v3
